weni/__init__.py
weni/components/__init__.py
weni/components/component.py
weni/context/__init__.py
weni/context/context.py
weni/context/preprocessor_context.py
weni/events/__init__.py
weni/events/event.py
weni/events/test_event.py
weni/preprocessor/__init__.py
weni/preprocessor/preprocessor.py
weni/responses/__init__.py
weni/responses/responses.py
weni/rules/__init__.py
weni/rules/rule.py
weni/tool/__init__.py
weni/tool/tool.py
weni/validators/__init__.py
weni/validators/validators.py
weni_agents_toolkit-2.3.2.dist-info/LICENSE
weni_agents_toolkit-2.3.2.dist-info/METADATA
weni_agents_toolkit-2.3.2.dist-info/WHEEL
weni_agents_toolkit-2.3.2.dist-info/RECORD
