Metadata-Version: 2.1
Name: weni-agents-toolkit
Version: 2.3.2
Summary: 
Author: Paulo Bernardo
Author-email: paulo.bernardo@weni.ai
Requires-Python: >=3.10
Classifier: Programming Language :: Python :: 3
Classifier: Programming Language :: Python :: 3.10
Classifier: Programming Language :: Python :: 3.11
Classifier: Programming Language :: Python :: 3.12
Classifier: Programming Language :: Python :: 3.13
